odoo/addons/hs_code_link/README.rst
odoo/addons/hs_code_link/__init__.py
odoo/addons/hs_code_link/__manifest__.py
odoo/addons/hs_code_link/i18n/es.po
odoo/addons/hs_code_link/i18n/hs_code_link.pot
odoo/addons/hs_code_link/models/__init__.py
odoo/addons/hs_code_link/models/product.py
odoo/addons/hs_code_link/readme/CONTRIBUTORS.rst
odoo/addons/hs_code_link/readme/DESCRIPTION.rst
odoo/addons/hs_code_link/readme/INSTALL.rst
odoo/addons/hs_code_link/static/description/icon.png
odoo/addons/hs_code_link/static/description/index.html
odoo/addons/hs_code_link/tests/__init__.py
odoo/addons/hs_code_link/tests/test_hs_code_link.py
odoo/addons/hs_code_link/views/product_views.xml
odoo13_addon_hs_code_link-13.0.2.0.0.dist-info/METADATA
odoo13_addon_hs_code_link-13.0.2.0.0.dist-info/WHEEL
odoo13_addon_hs_code_link-13.0.2.0.0.dist-info/top_level.txt
odoo13_addon_hs_code_link-13.0.2.0.0.dist-info/RECORD
